{
  "name": "Sunset Orange",
  "description": "Warm sunset-inspired theme with orange and red tones, perfect for creative applications",
  "version": "1.0",
  "author": "AvaloniaThemeManager",
  "createdDate": "2025-06-08T00:00:00Z",
  "primaryColor": "#FFFF6B35",
  "secondaryColor": "#FFFF8E53",
  "accentColor": "#FFFF4500",
  "primaryBackground": "#FF2D1B1B",
  "secondaryBackground": "#FF3D2829",
  "primaryTextColor": "#FFFFFFFF",
  "secondaryTextColor": "#FFFFD4B3",
  "borderColor": "#FFFF8E53",
  "errorColor": "#FFDC143C",
  "warningColor": "#FFFFA500",
  "successColor": "#FF32CD32",
  "fontFamily": "Segoe UI, San Francisco, Helvetica, Arial",
  "headerFontFamily": "Segoe UI, San Francisco, Helvetica, Arial",
  "bodyFontFamily": "Segoe UI, San Francisco, Helvetica, Arial",
  "monospaceFontFamily": "Consolas, Monaco, 'Courier New', monospace",
  "fontSizeSmall": 11,
  "fontSizeMedium": 13,
  "fontSizeLarge": 16,
  "fontWeight": "Normal",
  "lineHeight": 1.5,
  "letterSpacing": 0,
  "enableLigatures": true,
  "borderRadius": 6,
  "borderThickness": {
    "left": 1,
    "top": 1,
    "right": 1,
    "bottom": 1
  },
  "advancedTypography": {
    "displayLarge": 57,
    "displayMedium": 45,
    "displaySmall": 36,
    "headlineLarge": 32,
    "headlineMedium": 28,
    "headlineSmall": 24,
    "titleLarge": 22,
    "titleMedium": 16,
    "titleSmall": 14,
    "labelLarge": 14,
    "labelMedium": 12,
    "labelSmall": 11,
    "bodyLarge": 16,
    "bodyMedium": 14,
    "bodySmall": 12
  },
  "controlThemeUris": [
    "ControlThemes/TextBlock.axaml",
    "ControlThemes/Button.axaml"
  ],
  "styleUris": [],
  "assetUris": [],
  "baseSkin": null
}
